ofire/__init__.py
ofire/ofire.abi3.so
ofire-0.1.16.dist-info/METADATA
ofire-0.1.16.dist-info/WHEEL
ofire-0.1.16.dist-info/licenses/PYTHON_LICENSE
ofire-0.1.16.dist-info/RECORD
