Metadata-Version: 2.4
Name: ofire
Version: 0.1.16
Classifier: Programming Language :: Python :: 3
Classifier: Programming Language :: Rust
Classifier: Operating System :: OS Independent
License-File: PYTHON_LICENSE
License-File: PYTHON_LICENSE
Summary: A comprehensive Python package for fire safety engineering calculations and tools, providing implementations for industry standards like BR 187, BS 9999, CIBSE Guide E, PD 7974, SFPE Handbook, and more.
Keywords: fire,fire safety,fire engineering,BR 187,BS 9999,CIBSE Guide E,PD 7974,SFPE Handbook,Introduction to Fire Dynamics
Home-Page: https://github.com/emberon-tech/openfire
Author-email: EmberonTech <jamie@emberontech.com>
Requires-Python: >=3.8
Project-URL: Documentation, https://emberon-tech.github.io/openfire/
Project-URL: Homepage, https://www.openfiresoftware.com/
Project-URL: Repository, https://github.com/emberon-tech/openfire
